[
  {
    "client_msg_id": "c34a1d45-8cf3-4377-83be-498ffd5dc403",
    "type": "message",
    "user": "U056WKGF08M",
    "text": "are you all in the main zoom for the TA group ?",
    "ts": "1701392048.896559",
    "team": "T050CSX3EMT",
    "replace_original": false,
    "delete_original": false,
    "metadata": {
      "event_type": "",
      "event_payload": null
    },
    "blocks": [
      {
        "type": "rich_text",
        "block_id": "StsTQ",
        "elements": [
          {
            "type": "rich_text_section",
            "elements": [
              {
                "type": "text",
                "text": "are you all in the main zoom for the TA group ?"
              }
            ]
          }
        ]
      }
    ],
    "user_team": "T050CSX3EMT",
    "source_team": "T050CSX3EMT",
    "user_profile": {
      "avatar_hash": "",
      "image_72": "https://secure.gravatar.com/avatar/c51ce7c82041bfebaf5830e629de63cf.jpg?s=72\u0026d=https%3A%2F%2Fa.slack-edge.com%2Fdf10d%2Fimg%2Favatars%2Fava_0020-72.png",
      "first_name": "Kyaria",
      "real_name": "Kyaria Clemons",
      "display_name": "",
      "team": "T050CSX3EMT",
      "name": "kyarialove",
      "is_restricted": false,
      "is_ultra_restricted": false
    },
    "reply_users_count": 0,
    "reply_users": null
  },
  {
    "client_msg_id": "59e79861-282f-4da2-8db8-b4443c19c608",
    "type": "message",
    "user": "U056K1UHEGP",
    "text": "\u003chttps://docs.google.com/document/d/1T9d4kak64OfKIGu-yMGnxfPYyIQffeTaBNDkgynWXHc/edit?hl=en\u003e",
    "ts": "1701396084.147189",
    "team": "T050CSX3EMT",
    "replace_original": false,
    "delete_original": false,
    "metadata": {
      "event_type": "",
      "event_payload": null
    },
    "blocks": [
      {
        "type": "rich_text",
        "block_id": "1aj7U",
        "elements": [
          {
            "type": "rich_text_section",
            "elements": [
              {
                "type": "link",
                "url": "https://docs.google.com/document/d/1T9d4kak64OfKIGu-yMGnxfPYyIQffeTaBNDkgynWXHc/edit?hl=en",
                "text": ""
              }
            ]
          }
        ]
      }
    ],
    "user_team": "T050CSX3EMT",
    "source_team": "T050CSX3EMT",
    "user_profile": {
      "avatar_hash": "",
      "image_72": "https://secure.gravatar.com/avatar/13e306b805121fa81ffc3395068bf579.jpg?s=72\u0026d=https%3A%2F%2Fa.slack-edge.com%2Fdf10d%2Fimg%2Favatars%2Fava_0025-72.png",
      "first_name": "Sneha",
      "real_name": "Sneha Chitre",
      "display_name": "Sneha Chitre (KC)",
      "team": "T050CSX3EMT",
      "name": "sneha.chitre.usa",
      "is_restricted": false,
      "is_ultra_restricted": false
    },
    "reply_users_count": 0,
    "reply_users": null
  },
  {
    "client_msg_id": "D53A9D28-5A16-41F9-BAF9-E19AB2F9C7E5",
    "type": "message",
    "user": "U056K1UHEGP",
    "text": "Looks like Trello is out , we need to setup  GitHub projects ",
    "ts": "1701460568.000549",
    "thread_ts": "1701460568.000549",
    "reply_count": 1,
    "replies": [
      {
        "user": "U057UDJDKKJ",
        "ts": "1701464046.171499"
      }
    ],
    "latest_reply": "1701464046.171499",
    "files": [
      {
        "id": "F068CF4S6EQ",
        "created": 1701460485,
        "timestamp": 1701460485,
        "name": "IMG_1107.png",
        "title": "IMG_1107",
        "mimetype": "image/png",
        "image_exif_rotation": 0,
        "filetype": "png",
        "pretty_type": "PNG",
        "user": "U056K1UHEGP",
        "mode": "hosted",
        "editable": false,
        "is_external": false,
        "external_type": "",
        "size": 332014,
        "url": "",
        "url_download": "",
        "url_private": "https://files.slack.com/files-pri/T050CSX3EMT-F068CF4S6EQ/img_1107.png",
        "url_private_download": "https://files.slack.com/files-pri/T050CSX3EMT-F068CF4S6EQ/download/img_1107.png",
        "original_h": 2532,
        "original_w": 1170,
        "thumb_64": "https://files.slack.com/files-tmb/T050CSX3EMT-F068CF4S6EQ-a38ed45ab5/img_1107_64.png",
        "thumb_80": "https://files.slack.com/files-tmb/T050CSX3EMT-F068CF4S6EQ-a38ed45ab5/img_1107_80.png",
        "thumb_160": "https://files.slack.com/files-tmb/T050CSX3EMT-F068CF4S6EQ-a38ed45ab5/img_1107_160.png",
        "thumb_360": "https://files.slack.com/files-tmb/T050CSX3EMT-F068CF4S6EQ-a38ed45ab5/img_1107_360.png",
        "thumb_360_gif": "",
        "thumb_360_w": 166,
        "thumb_360_h": 360,
        "thumb_480": "https://files.slack.com/files-tmb/T050CSX3EMT-F068CF4S6EQ-a38ed45ab5/img_1107_480.png",
        "thumb_480_w": 222,
        "thumb_480_h": 480,
        "thumb_720": "https://files.slack.com/files-tmb/T050CSX3EMT-F068CF4S6EQ-a38ed45ab5/img_1107_720.png",
        "thumb_720_w": 333,
        "thumb_720_h": 720,
        "thumb_960": "https://files.slack.com/files-tmb/T050CSX3EMT-F068CF4S6EQ-a38ed45ab5/img_1107_960.png",
        "thumb_960_w": 444,
        "thumb_960_h": 960,
        "thumb_1024": "https://files.slack.com/files-tmb/T050CSX3EMT-F068CF4S6EQ-a38ed45ab5/img_1107_1024.png",
        "thumb_1024_w": 473,
        "thumb_1024_h": 1024,
        "permalink": "https://ptwebdevallhu-iu32728.slack.com/files/U056K1UHEGP/F068CF4S6EQ/img_1107.png",
        "permalink_public": "https://slack-files.com/T050CSX3EMT-F068CF4S6EQ-990b216318",
        "edit_link": "",
        "preview": "",
        "preview_highlight": "",
        "lines": 0,
        "lines_more": 0,
        "is_public": true,
        "public_url_shared": false,
        "channels": null,
        "groups": null,
        "ims": null,
        "initial_comment": {},
        "comments_count": 0,
        "num_stars": 0,
        "is_starred": false,
        "shares": {
          "public": null,
          "private": null
        }
      }
    ],
    "replace_original": false,
    "delete_original": false,
    "metadata": {
      "event_type": "",
      "event_payload": null
    },
    "blocks": [
      {
        "type": "rich_text",
        "block_id": "gcmfF",
        "elements": [
          {
            "type": "rich_text_section",
            "elements": [
              {
                "type": "text",
                "text": "Looks like Trello is out , we need to setup  GitHub projects "
              }
            ]
          }
        ]
      }
    ],
    "user_team": "",
    "source_team": "",
    "user_profile": {
      "avatar_hash": "",
      "image_72": "https://secure.gravatar.com/avatar/13e306b805121fa81ffc3395068bf579.jpg?s=72\u0026d=https%3A%2F%2Fa.slack-edge.com%2Fdf10d%2Fimg%2Favatars%2Fava_0025-72.png",
      "first_name": "Sneha",
      "real_name": "Sneha Chitre",
      "display_name": "Sneha Chitre (KC)",
      "team": "T050CSX3EMT",
      "name": "sneha.chitre.usa",
      "is_restricted": false,
      "is_ultra_restricted": false
    },
    "reply_users_count": 1,
    "reply_users": [
      "U057UDJDKKJ"
    ]
  },
  {
    "client_msg_id": "8453ecef-36ed-4352-a0cd-3c5bebb50c17",
    "type": "message",
    "user": "U057UDJDKKJ",
    "text": "noted! I'll look over everything this weekend to make sure our tasks are updated on github projects",
    "ts": "1701464046.171499",
    "thread_ts": "1701460568.000549",
    "parent_user_id": "U056K1UHEGP",
    "team": "T050CSX3EMT",
    "reactions": [
      {
        "name": "+1::skin-tone-3",
        "count": 1,
        "users": [
          "U056K1UHEGP"
        ]
      }
    ],
    "replace_original": false,
    "delete_original": false,
    "metadata": {
      "event_type": "",
      "event_payload": null
    },
    "blocks": [
      {
        "type": "rich_text",
        "block_id": "s1Zx5",
        "elements": [
          {
            "type": "rich_text_section",
            "elements": [
              {
                "type": "text",
                "text": "noted! I'll look over everything this weekend to make sure our tasks are updated on github projects"
              }
            ]
          }
        ]
      }
    ],
    "user_team": "T050CSX3EMT",
    "source_team": "T050CSX3EMT",
    "user_profile": {
      "avatar_hash": "",
      "image_72": "https://avatars.slack-edge.com/2023-05-10/5245349121076_71afb28372a000533ca2_72.jpg",
      "first_name": "Jenna",
      "real_name": "Jenna Tan",
      "display_name": "Jenna Tan (Philly)",
      "team": "T050CSX3EMT",
      "name": "jmt9088",
      "is_restricted": false,
      "is_ultra_restricted": false
    },
    "reply_users_count": 0,
    "reply_users": null
  }
]
