[
  {
    "client_msg_id": "b996ab6e-e6bc-4dfe-a285-185d5ef02349",
    "type": "message",
    "user": "U057UDJDKKJ",
    "text": "\u003c@U0625KF6RLH\u003e will there be a template for presenting as a group?",
    "ts": "1704767616.335609",
    "thread_ts": "1704767616.335609",
    "reply_count": 5,
    "replies": [
      {
        "user": "U056Q9W022K",
        "ts": "1704776003.112559"
      },
      {
        "user": "U056Q9W022K",
        "ts": "1704776018.650599"
      },
      {
        "user": "U057UDJDKKJ",
        "ts": "1704805668.968969"
      },
      {
        "user": "U056Q9W022K",
        "ts": "1704808976.037769"
      },
      {
        "user": "U0625KF6RLH",
        "ts": "1704813251.203669"
      }
    ],
    "latest_reply": "1704813251.203669",
    "team": "T050CSX3EMT",
    "replace_original": false,
    "delete_original": false,
    "metadata": {
      "event_type": "",
      "event_payload": null
    },
    "blocks": [
      {
        "type": "rich_text",
        "block_id": "P0U+5",
        "elements": [
          {
            "type": "rich_text_section",
            "elements": [
              {
                "type": "user",
                "user_id": "U0625KF6RLH"
              },
              {
                "type": "text",
                "text": " will there be a template for presenting as a group?"
              }
            ]
          }
        ]
      }
    ],
    "user_team": "T050CSX3EMT",
    "source_team": "T050CSX3EMT",
    "user_profile": {
      "avatar_hash": "",
      "image_72": "https://avatars.slack-edge.com/2023-05-10/5245349121076_71afb28372a000533ca2_72.jpg",
      "first_name": "Jenna",
      "real_name": "Jenna Tan",
      "display_name": "Jenna Tan (Philly)",
      "team": "T050CSX3EMT",
      "name": "jmt9088",
      "is_restricted": false,
      "is_ultra_restricted": false
    },
    "reply_users_count": 3,
    "reply_users": [
      "U056Q9W022K",
      "U057UDJDKKJ",
      "U0625KF6RLH"
    ]
  },
  {
    "client_msg_id": "84b7ef25-4651-480b-9291-ba8fe6b47a73",
    "type": "message",
    "user": "U056Q9W022K",
    "text": "I'm not sure if this is why you are asking or if it's unrelated, but making sure you know that demos  on the 18th are individual not as a group.",
    "ts": "1704776003.112559",
    "thread_ts": "1704767616.335609",
    "parent_user_id": "U057UDJDKKJ",
    "team": "T050CSX3EMT",
    "replace_original": false,
    "delete_original": false,
    "metadata": {
      "event_type": "",
      "event_payload": null
    },
    "blocks": [
      {
        "type": "rich_text",
        "block_id": "Aya/l",
        "elements": [
          {
            "type": "rich_text_section",
            "elements": [
              {
                "type": "text",
                "text": "I'm not sure if this is why you are asking or if it's unrelated, but making sure you know that demos  on the 18th are individual not as a group."
              }
            ]
          }
        ]
      }
    ],
    "user_team": "T050CSX3EMT",
    "source_team": "T050CSX3EMT",
    "user_profile": {
      "avatar_hash": "",
      "image_72": "https://avatars.slack-edge.com/2023-05-18/5313581523280_e6c244d910e46b3ed94c_72.png",
      "first_name": "Erin",
      "real_name": "Erin Muzughi",
      "display_name": "Erin Muzughi (STL)",
      "team": "T050CSX3EMT",
      "name": "erinmuzughi",
      "is_restricted": false,
      "is_ultra_restricted": false
    },
    "reply_users_count": 0,
    "reply_users": null
  },
  {
    "client_msg_id": "f0e486ca-287f-4e05-94f9-56e8110cbdd5",
    "type": "message",
    "user": "U056Q9W022K",
    "text": "(here is how I know that: \u003chttps://ptwebdevallhu-iu32728.slack.com/archives/C05099VL15L/p1704412830216469?thread_ts=1704412672.009889\u0026amp;cid=C05099VL15L\u003e)",
    "ts": "1704776018.650599",
    "thread_ts": "1704767616.335609",
    "attachments": [
      {
        "fallback": "[January 4th, 2024 4:00 PM] lexi: It will be individual!",
        "id": 1,
        "author_id": "U066ED0A4DU",
        "author_name": "Lexi B",
        "author_subname": "Lexi B",
        "author_link": "https://ptwebdevallhu-iu32728.slack.com/team/U066ED0A4DU",
        "author_icon": "https://avatars.slack-edge.com/2023-11-20/6222153280613_25c32eb42d9b05bf45f0_48.png",
        "text": "It will be individual!",
        "from_url": "https://ptwebdevallhu-iu32728.slack.com/archives/C05099VL15L/p1704412830216469?thread_ts=1704412672.009889\u0026amp;cid=C05099VL15L",
        "original_url": "https://ptwebdevallhu-iu32728.slack.com/archives/C05099VL15L/p1704412830216469?thread_ts=1704412672.009889\u0026amp;cid=C05099VL15L",
        "mrkdwn_in": [
          "text"
        ],
        "blocks": null,
        "footer": "Thread in Slack Conversation",
        "ts": 1704412830.216469
      }
    ],
    "parent_user_id": "U057UDJDKKJ",
    "team": "T050CSX3EMT",
    "replace_original": false,
    "delete_original": false,
    "metadata": {
      "event_type": "",
      "event_payload": null
    },
    "blocks": [
      {
        "type": "rich_text",
        "block_id": "/0v4v",
        "elements": [
          {
            "type": "rich_text_section",
            "elements": [
              {
                "type": "text",
                "text": "(here is how I know that: "
              },
              {
                "type": "link",
                "url": "https://ptwebdevallhu-iu32728.slack.com/archives/C05099VL15L/p1704412830216469?thread_ts=1704412672.009889\u0026cid=C05099VL15L",
                "text": ""
              },
              {
                "type": "text",
                "text": ")"
              }
            ]
          }
        ]
      }
    ],
    "user_team": "T050CSX3EMT",
    "source_team": "T050CSX3EMT",
    "user_profile": {
      "avatar_hash": "",
      "image_72": "https://avatars.slack-edge.com/2023-05-18/5313581523280_e6c244d910e46b3ed94c_72.png",
      "first_name": "Erin",
      "real_name": "Erin Muzughi",
      "display_name": "Erin Muzughi (STL)",
      "team": "T050CSX3EMT",
      "name": "erinmuzughi",
      "is_restricted": false,
      "is_ultra_restricted": false
    },
    "reply_users_count": 0,
    "reply_users": null
  },
  {
    "client_msg_id": "d214b8e6-001a-4add-88da-54125a337875",
    "type": "message",
    "user": "U057UDJDKKJ",
    "text": "oh i did not see that! yup that answers my question, thanks so much Erin :blush:",
    "ts": "1704805668.968969",
    "thread_ts": "1704767616.335609",
    "parent_user_id": "U057UDJDKKJ",
    "team": "T050CSX3EMT",
    "replace_original": false,
    "delete_original": false,
    "metadata": {
      "event_type": "",
      "event_payload": null
    },
    "blocks": [
      {
        "type": "rich_text",
        "block_id": "Rvr2M",
        "elements": [
          {
            "type": "rich_text_section",
            "elements": [
              {
                "type": "text",
                "text": "oh i did not see that! yup that answers my question, thanks so much Erin "
              },
              {
                "type": "emoji",
                "name": "blush",
                "skin_tone": 0
              }
            ]
          }
        ]
      }
    ],
    "user_team": "T050CSX3EMT",
    "source_team": "T050CSX3EMT",
    "user_profile": {
      "avatar_hash": "",
      "image_72": "https://avatars.slack-edge.com/2023-05-10/5245349121076_71afb28372a000533ca2_72.jpg",
      "first_name": "Jenna",
      "real_name": "Jenna Tan",
      "display_name": "Jenna Tan (Philly)",
      "team": "T050CSX3EMT",
      "name": "jmt9088",
      "is_restricted": false,
      "is_ultra_restricted": false
    },
    "reply_users_count": 0,
    "reply_users": null
  },
  {
    "client_msg_id": "0DA6623F-464D-4A8C-BE64-8CB7E2D3D6C6",
    "type": "message",
    "user": "U056Q9W022K",
    "text": "No problem!",
    "ts": "1704808976.037769",
    "thread_ts": "1704767616.335609",
    "parent_user_id": "U057UDJDKKJ",
    "team": "T050CSX3EMT",
    "replace_original": false,
    "delete_original": false,
    "metadata": {
      "event_type": "",
      "event_payload": null
    },
    "blocks": [
      {
        "type": "rich_text",
        "block_id": "zyA6Y",
        "elements": [
          {
            "type": "rich_text_section",
            "elements": [
              {
                "type": "text",
                "text": "No problem!"
              }
            ]
          }
        ]
      }
    ],
    "user_team": "T050CSX3EMT",
    "source_team": "T050CSX3EMT",
    "user_profile": {
      "avatar_hash": "",
      "image_72": "https://avatars.slack-edge.com/2023-05-18/5313581523280_e6c244d910e46b3ed94c_72.png",
      "first_name": "Erin",
      "real_name": "Erin Muzughi",
      "display_name": "Erin Muzughi (STL)",
      "team": "T050CSX3EMT",
      "name": "erinmuzughi",
      "is_restricted": false,
      "is_ultra_restricted": false
    },
    "reply_users_count": 0,
    "reply_users": null
  },
  {
    "client_msg_id": "07CA29E0-A431-421B-8F6B-A531B86338B2",
    "type": "message",
    "user": "U056K1UHEGP",
    "text": "Oh! So we will demo all project to show how it works but will have individual presentation focusing our part in it ? ",
    "ts": "1704809993.935869",
    "thread_ts": "1704412672.009889",
    "parent_user_id": "U057BDJE6GM",
    "team": "T050CSX3EMT",
    "replace_original": false,
    "delete_original": false,
    "metadata": {
      "event_type": "",
      "event_payload": null
    },
    "blocks": [
      {
        "type": "rich_text",
        "block_id": "3ZC/H",
        "elements": [
          {
            "type": "rich_text_section",
            "elements": [
              {
                "type": "text",
                "text": "Oh! So we will demo all project to show how it works but will have individual presentation focusing our part in it ? "
              }
            ]
          }
        ]
      }
    ],
    "user_team": "T050CSX3EMT",
    "source_team": "T050CSX3EMT",
    "user_profile": {
      "avatar_hash": "",
      "image_72": "https://secure.gravatar.com/avatar/13e306b805121fa81ffc3395068bf579.jpg?s=72\u0026d=https%3A%2F%2Fa.slack-edge.com%2Fdf10d%2Fimg%2Favatars%2Fava_0025-72.png",
      "first_name": "Sneha",
      "real_name": "Sneha Chitre",
      "display_name": "Sneha Chitre (KC)",
      "team": "T050CSX3EMT",
      "name": "sneha.chitre.usa",
      "is_restricted": false,
      "is_ultra_restricted": false
    },
    "reply_users_count": 0,
    "reply_users": null
  },
  {
    "client_msg_id": "ca2a1492-5121-4792-a2a9-69c918328c3d",
    "type": "message",
    "user": "U0625KF6RLH",
    "text": "Yep! Erin's got it again. Project Demos are individual as are all grades in Liftoff.",
    "ts": "1704813251.203669",
    "thread_ts": "1704767616.335609",
    "parent_user_id": "U057UDJDKKJ",
    "team": "T050CSX3EMT",
    "reactions": [
      {
        "name": "heart",
        "count": 1,
        "users": [
          "U057UDJDKKJ"
        ]
      }
    ],
    "replace_original": false,
    "delete_original": false,
    "metadata": {
      "event_type": "",
      "event_payload": null
    },
    "blocks": [
      {
        "type": "rich_text",
        "block_id": "xwtnH",
        "elements": [
          {
            "type": "rich_text_section",
            "elements": [
              {
                "type": "text",
                "text": "Yep! Erin's got it again. Project Demos are individual as are all grades in Liftoff."
              }
            ]
          }
        ]
      }
    ],
    "user_team": "T050CSX3EMT",
    "source_team": "T050CSX3EMT",
    "user_profile": {
      "avatar_hash": "",
      "image_72": "https://avatars.slack-edge.com/2023-10-19/6068347004260_cd7e855b65583e9c6d43_72.jpg",
      "first_name": "Melinda",
      "real_name": "Melinda Stitzel",
      "display_name": "Liftoff Program Manager - Melinda (she/her)",
      "team": "T050CSX3EMT",
      "name": "melinda",
      "is_restricted": false,
      "is_ultra_restricted": false
    },
    "reply_users_count": 0,
    "reply_users": null
  }
]
