[
  {
    "client_msg_id": "805bdcb8-a38e-467b-9db3-c898d9779001",
    "type": "message",
    "user": "U056SVBQSES",
    "text": "Thanks so much, Alex!! It was really great having you as a TA not only now but also in Unit 1!",
    "ts": "1706228709.272449",
    "thread_ts": "1706226583.687289",
    "parent_user_id": "U05EE11SB6D",
    "team": "T050CSX3EMT",
    "reactions": [
      {
        "name": "heart",
        "count": 1,
        "users": [
          "U05EE11SB6D"
        ]
      }
    ],
    "replace_original": false,
    "delete_original": false,
    "metadata": {
      "event_type": "",
      "event_payload": null
    },
    "blocks": [
      {
        "type": "rich_text",
        "block_id": "K39/7",
        "elements": [
          {
            "type": "rich_text_section",
            "elements": [
              {
                "type": "text",
                "text": "Thanks so much, Alex!! It was really great having you as a TA not only now but also in Unit 1!"
              }
            ]
          }
        ]
      }
    ],
    "user_team": "T050CSX3EMT",
    "source_team": "T050CSX3EMT",
    "user_profile": {
      "avatar_hash": "",
      "image_72": "https://avatars.slack-edge.com/2023-05-11/5274449962768_b6d8928e25cd1da2d413_72.jpg",
      "first_name": "Jose",
      "real_name": "Jose Pablo (JP) Barragan",
      "display_name": "JP Barragan",
      "team": "T050CSX3EMT",
      "name": "jpbarragann",
      "is_restricted": false,
      "is_ultra_restricted": false
    },
    "reply_users_count": 0,
    "reply_users": null
  },
  {
    "client_msg_id": "9cb6c7e8-69cc-4af5-9730-e535f9006d19",
    "type": "message",
    "user": "U057HDRTJU9",
    "text": "I feel fortunate to have had the opportunity to learn from someone as dedicated and passionate as you... Thankyou Alex!!:innocent:",
    "ts": "1706228786.568799",
    "thread_ts": "1706226583.687289",
    "parent_user_id": "U05EE11SB6D",
    "team": "T050CSX3EMT",
    "reactions": [
      {
        "name": "heart",
        "count": 1,
        "users": [
          "U05EE11SB6D"
        ]
      }
    ],
    "replace_original": false,
    "delete_original": false,
    "metadata": {
      "event_type": "",
      "event_payload": null
    },
    "blocks": [
      {
        "type": "rich_text",
        "block_id": "8GNi2",
        "elements": [
          {
            "type": "rich_text_section",
            "elements": [
              {
                "type": "text",
                "text": "I feel fortunate to have had the opportunity to learn from someone as dedicated and passionate as you... Thankyou Alex!!"
              },
              {
                "type": "emoji",
                "name": "innocent",
                "skin_tone": 0
              }
            ]
          }
        ]
      }
    ],
    "user_team": "T050CSX3EMT",
    "source_team": "T050CSX3EMT",
    "user_profile": {
      "avatar_hash": "",
      "image_72": "https://avatars.slack-edge.com/2023-05-10/5243080667203_61e07f4b1448b0bfad86_72.jpg",
      "first_name": "Charu",
      "real_name": "Charu",
      "display_name": "",
      "team": "T050CSX3EMT",
      "name": "charu91.sathish",
      "is_restricted": false,
      "is_ultra_restricted": false
    },
    "reply_users_count": 0,
    "reply_users": null
  },
  {
    "client_msg_id": "61065337-DE83-4CD3-B3B6-13A7F3B169B2",
    "type": "message",
    "user": "U057S95RQC9",
    "text": "Thank you so much, Alex! You’re a great TA and I’m very grateful to have had the opportunity to learn from you and to had your support throughout this unit! :pray: :blush: ",
    "ts": "1706229009.778669",
    "thread_ts": "1706226583.687289",
    "parent_user_id": "U05EE11SB6D",
    "team": "T050CSX3EMT",
    "reactions": [
      {
        "name": "heart",
        "count": 1,
        "users": [
          "U05EE11SB6D"
        ]
      }
    ],
    "replace_original": false,
    "delete_original": false,
    "metadata": {
      "event_type": "",
      "event_payload": null
    },
    "blocks": [
      {
        "type": "rich_text",
        "block_id": "lE8Li",
        "elements": [
          {
            "type": "rich_text_section",
            "elements": [
              {
                "type": "text",
                "text": "Thank you so much, Alex! "
              },
              {
                "type": "text",
                "text": "You’re"
              },
              {
                "type": "text",
                "text": " a great TA and "
              },
              {
                "type": "text",
                "text": "I’m"
              },
              {
                "type": "text",
                "text": " very grateful to have had the opportunity to learn from you and to had your support throughout this unit! "
              },
              {
                "type": "emoji",
                "name": "pray",
                "skin_tone": 0
              },
              {
                "type": "text",
                "text": " "
              },
              {
                "type": "emoji",
                "name": "blush",
                "skin_tone": 0
              },
              {
                "type": "text",
                "text": " "
              }
            ]
          }
        ]
      }
    ],
    "user_team": "T050CSX3EMT",
    "source_team": "T050CSX3EMT",
    "user_profile": {
      "avatar_hash": "",
      "image_72": "https://avatars.slack-edge.com/2023-11-28/6255059219110_09fcfa42a8921f231618_72.jpg",
      "first_name": "Jialing",
      "real_name": "Jialing Liu",
      "display_name": "Jialing Liu",
      "team": "T050CSX3EMT",
      "name": "jialingl.liu",
      "is_restricted": false,
      "is_ultra_restricted": false
    },
    "reply_users_count": 0,
    "reply_users": null
  }
]
